README.md
setup.py
pr_dir.egg-info/PKG-INFO
pr_dir.egg-info/SOURCES.txt
pr_dir.egg-info/dependency_links.txt
pr_dir.egg-info/top_level.txt
print_dir/__init__.py
print_dir/visualizer.py
tests/__init__.py
tests/test_Visualizer.py