Metadata-Version: 2.1
Name: pr-dir
Version: 1.0.0
Summary: Directory`s files console-visualizer
Home-page: https://github.com/gideko1/print_dir
Author: Tarasenko V.E.
Author-email: gidekoj@mail.ru
License: UNKNOWN
Platform: any
Requires-Python: >=3.7
